otSpec/__init__.py
otSpec/cpg/__init__.py
otSpec/cpg/data.txt
otSpec/cpg/update.py
otSpec/table/GPOS.py
otSpec/table/GSUB.py
otSpec/table/MVAR.py
otSpec/table/OS2.py
otSpec/table/STAT.py
otSpec/table/__init__.py
otSpec/table/gasp.py
otSpec/table/head.py
otSpec/table/name.py
otSpec/tag/__init__.py
otSpec/tag/feature.py
otSpec/tag/language.py
otSpec/tag/script.py
otSpec-0.1.34.dist-info/LICENSE
otSpec-0.1.34.dist-info/METADATA
otSpec-0.1.34.dist-info/WHEEL
otSpec-0.1.34.dist-info/top_level.txt
otSpec-0.1.34.dist-info/RECORD
